{
	"required": true,
	"package": "me.ghluka.medved.mixin.client",
	"compatibilityLevel": "JAVA_25",
	"client": [
		"CameraMixin",
		"ClientPacketListenerMixin",
		"ConnectionMixin",
		"DeltaTrackerMixin",
		"EntityMixin",
		"ItemCooldownsMixin",
		"JoinMultiplayerScreenMixin",
		"KeyboardInputMixin",
		"LivingEntityAccessor",
		"LivingEntityMixin",
		"LocalPlayerAccessor",
		"LocalPlayerMixin",
		"MinecraftAccessor",
		"MinecraftMixin",
		"MinecraftUserAccessor",
		"MultiPlayerGameModeMixin",
		"PlayerMixin",
		"TitleScreenMixin"
	],
	"injectors": {
		"defaultRequire": 1
	},
	"overwrites": {
		"requireAnnotations": true
	}
}